{
    "data": {
        "id": "c919759d-70d4-4b55-bd76-51fa577894d7",
        "user_id": "d44d9645-f329-4729-a92d-c1c4ce039e23",
        "range": "last_7_days",
        "start": "2026-01-19T23:00:00Z",
        "end": "2026-01-26T22:59:59Z",
        "timeout": 15,
        "writes_only": false,
        "timezone": "Europe/Paris",
        "ai_additions": 0,
        "ai_deletions": 0,
        "human_additions": 0,
        "human_deletions": 0,
        "holidays": 1,
        "status": "ok",
        "created_at": "2026-01-16T03:02:17Z",
        "modified_at": "2026-01-27T02:39:46Z",
        "projects": [
            {
                "total_seconds": 123975.293,
                "name": "portefolio",
                "ai_additions": 0,
                "ai_deletions": 0,
                "human_additions": 0,
                "human_deletions": 0,
                "percent": 85.92,
                "digital": "34:26",
                "decimal": "34.43",
                "text": "34 hrs 26 mins",
                "hours": 34,
                "minutes": 26
            },
            {
                "total_seconds": 17489.276,
                "name": "bat_track_v1",
                "ai_additions": 0,
                "ai_deletions": 0,
                "human_additions": 0,
                "human_deletions": 0,
                "percent": 12.12,
                "digital": "4:51",
                "decimal": "4.85",
                "text": "4 hrs 51 mins",
                "hours": 4,
                "minutes": 51
            },
            {
                "total_seconds": 2800.188,
                "name": "3.35.2",
                "ai_additions": 0,
                "ai_deletions": 0,
                "human_additions": 0,
                "human_deletions": 0,
                "percent": 1.94,
                "digital": "0:46",
                "decimal": "0.77",
                "text": "46 mins",
                "hours": 0,
                "minutes": 46
            },
            {
                "total_seconds": 31.533,
                "name": "stable",
                "ai_additions": 0,
                "ai_deletions": 0,
                "human_additions": 0,
                "human_deletions": 0,
                "percent": 0.02,
                "digital": "0:00",
                "decimal": "0.00",
                "text": "0 secs",
                "hours": 0,
                "minutes": 0
            },
            {
                "total_seconds": 1.994,
                "name": "flutter_sdk",
                "ai_additions": 0,
                "ai_deletions": 0,
                "human_additions": 0,
                "human_deletions": 0,
                "percent": 0.0,
                "digital": "0:00",
                "decimal": "0.00",
                "text": "0 secs",
                "hours": 0,
                "minutes": 0
            }
        ],
        "days_minus_holidays": 6,
        "daily_average_including_other_language": 24050.0,
        "is_stuck": false,
        "days_including_holidays": 7,
        "is_already_updating": false,
        "editors": [
            {
                "total_seconds": 144298.284,
                "name": "Android Studio",
                "percent": 100.0,
                "digital": "40:04",
                "decimal": "40.07",
                "text": "40 hrs 4 mins",
                "hours": 40,
                "minutes": 4
            }
        ],
        "operating_systems": [
            {
                "total_seconds": 144298.284,
                "name": "Windows",
                "percent": 100.0,
                "digital": "40:04",
                "decimal": "40.07",
                "text": "40 hrs 4 mins",
                "hours": 40,
                "minutes": 4
            }
        ],
        "machines": [
            {
                "total_seconds": 144298.284,
                "name": "LAPTOP-CUKQT8S6",
                "machine_name_id": "018e87a1-bc6e-4704-bac3-601dd20fbd21",
                "percent": 100.0,
                "digital": "40:04",
                "decimal": "40.07",
                "text": "40 hrs 4 mins",
                "hours": 40,
                "minutes": 4
            }
        ],
        "categories": [
            {
                "name": "Coding",
                "total_seconds": 139336.637,
                "percent": 96.56,
                "digital": "38:42",
                "decimal": "38.70",
                "text": "38 hrs 42 mins",
                "hours": 38,
                "minutes": 42
            },
            {
                "name": "Writing Tests",
                "total_seconds": 4958.634,
                "percent": 3.44,
                "digital": "1:22",
                "decimal": "1.37",
                "text": "1 hr 22 mins",
                "hours": 1,
                "minutes": 22
            },
            {
                "name": "Writing Docs",
                "total_seconds": 3.013,
                "percent": 0.0,
                "digital": "0:00",
                "decimal": "0.00",
                "text": "0 secs",
                "hours": 0,
                "minutes": 0
            }
        ],
        "daily_average": 24050.0,
        "is_up_to_date_pending_future": false,
        "best_day": {
            "date": "2026-01-22",
            "total_seconds": 34244.753,
            "text": "9 hrs 30 mins"
        },
        "human_readable_daily_average_including_other_language": "6 hrs 40 mins",
        "is_up_to_date": true,
        "human_readable_total_including_other_language": "40 hrs 4 mins",
        "dependencies": [
            {
                "total_seconds": 2076.437,
                "name": "PIL",
                "percent": 10.57,
                "digital": "0:34",
                "decimal": "0.57",
                "text": "34 mins",
                "hours": 0,
                "minutes": 34
            },
            {
                "total_seconds": 2076.437,
                "name": "typing",
                "percent": 10.57,
                "digital": "0:34",
                "decimal": "0.57",
                "text": "34 mins",
                "hours": 0,
                "minutes": 34
            },
            {
                "total_seconds": 2076.437,
                "name": "shutil",
                "percent": 10.57,
                "digital": "0:34",
                "decimal": "0.57",
                "text": "34 mins",
                "hours": 0,
                "minutes": 34
            },
            {
                "total_seconds": 2076.437,
                "name": "tqdm",
                "percent": 10.57,
                "digital": "0:34",
                "decimal": "0.57",
                "text": "34 mins",
                "hours": 0,
                "minutes": 34
            },
            {
                "total_seconds": 2076.437,
                "name": "argparse",
                "percent": 10.57,
                "digital": "0:34",
                "decimal": "0.57",
                "text": "34 mins",
                "hours": 0,
                "minutes": 34
            },
            {
                "total_seconds": 2076.437,
                "name": "pathlib",
                "percent": 10.57,
                "digital": "0:34",
                "decimal": "0.57",
                "text": "34 mins",
                "hours": 0,
                "minutes": 34
            },
            {
                "total_seconds": 326.45,
                "name": "is_coding_activity_visible",
                "percent": 1.66,
                "digital": "0:05",
                "decimal": "0.08",
                "text": "5 mins",
                "hours": 0,
                "minutes": 5
            },
            {
                "total_seconds": 326.45,
                "name": "projects",
                "percent": 1.66,
                "digital": "0:05",
                "decimal": "0.08",
                "text": "5 mins",
                "hours": 0,
                "minutes": 5
            },
            {
                "total_seconds": 326.45,
                "name": "human_readable_total",
                "percent": 1.66,
                "digital": "0:05",
                "decimal": "0.08",
                "text": "5 mins",
                "hours": 0,
                "minutes": 5
            },
            {
                "total_seconds": 326.45,
                "name": "daily_average",
                "percent": 1.66,
                "digital": "0:05",
                "decimal": "0.08",
                "text": "5 mins",
                "hours": 0,
                "minutes": 5
            },
            {
                "total_seconds": 326.45,
                "name": "is_cached",
                "percent": 1.66,
                "digital": "0:05",
                "decimal": "0.08",
                "text": "5 mins",
                "hours": 0,
                "minutes": 5
            },
            {
                "total_seconds": 326.45,
                "name": "human_readable_daily_average",
                "percent": 1.66,
                "digital": "0:05",
                "decimal": "0.08",
                "text": "5 mins",
                "hours": 0,
                "minutes": 5
            },
            {
                "total_seconds": 326.45,
                "name": "is_os_usage_visible",
                "percent": 1.66,
                "digital": "0:05",
                "decimal": "0.08",
                "text": "5 mins",
                "hours": 0,
                "minutes": 5
            },
            {
                "total_seconds": 326.45,
                "name": "categories",
                "percent": 1.66,
                "digital": "0:05",
                "decimal": "0.08",
                "text": "5 mins",
                "hours": 0,
                "minutes": 5
            },
            {
                "total_seconds": 326.45,
                "name": "is_including_today",
                "percent": 1.66,
                "digital": "0:05",
                "decimal": "0.08",
                "text": "5 mins",
                "hours": 0,
                "minutes": 5
            },
            {
                "total_seconds": 326.45,
                "name": "best_day",
                "percent": 1.66,
                "digital": "0:05",
                "decimal": "0.08",
                "text": "5 mins",
                "hours": 0,
                "minutes": 5
            },
            {
                "total_seconds": 326.45,
                "name": "username",
                "percent": 1.66,
                "digital": "0:05",
                "decimal": "0.08",
                "text": "5 mins",
                "hours": 0,
                "minutes": 5
            },
            {
                "total_seconds": 326.45,
                "name": "is_up_to_date_pending_future",
                "percent": 1.66,
                "digital": "0:05",
                "decimal": "0.08",
                "text": "5 mins",
                "hours": 0,
                "minutes": 5
            },
            {
                "total_seconds": 326.45,
                "name": "is_already_updating",
                "percent": 1.66,
                "digital": "0:05",
                "decimal": "0.08",
                "text": "5 mins",
                "hours": 0,
                "minutes": 5
            },
            {
                "total_seconds": 326.45,
                "name": "is_category_usage_visible",
                "percent": 1.66,
                "digital": "0:05",
                "decimal": "0.08",
                "text": "5 mins",
                "hours": 0,
                "minutes": 5
            },
            {
                "total_seconds": 326.45,
                "name": "is_language_usage_visible",
                "percent": 1.66,
                "digital": "0:05",
                "decimal": "0.08",
                "text": "5 mins",
                "hours": 0,
                "minutes": 5
            },
            {
                "total_seconds": 326.45,
                "name": "is_stuck",
                "percent": 1.66,
                "digital": "0:05",
                "decimal": "0.08",
                "text": "5 mins",
                "hours": 0,
                "minutes": 5
            },
            {
                "total_seconds": 326.45,
                "name": "editors",
                "percent": 1.66,
                "digital": "0:05",
                "decimal": "0.08",
                "text": "5 mins",
                "hours": 0,
                "minutes": 5
            },
            {
                "total_seconds": 326.45,
                "name": "is_up_to_date",
                "percent": 1.66,
                "digital": "0:05",
                "decimal": "0.08",
                "text": "5 mins",
                "hours": 0,
                "minutes": 5
            },
            {
                "total_seconds": 326.45,
                "name": "daily_average_including_other_language",
                "percent": 1.66,
                "digital": "0:05",
                "decimal": "0.08",
                "text": "5 mins",
                "hours": 0,
                "minutes": 5
            },
            {
                "total_seconds": 326.45,
                "name": "human_readable_range",
                "percent": 1.66,
                "digital": "0:05",
                "decimal": "0.08",
                "text": "5 mins",
                "hours": 0,
                "minutes": 5
            },
            {
                "total_seconds": 326.45,
                "name": "operating_systems",
                "percent": 1.66,
                "digital": "0:05",
                "decimal": "0.08",
                "text": "5 mins",
                "hours": 0,
                "minutes": 5
            },
            {
                "total_seconds": 326.45,
                "name": "is_editor_usage_visible",
                "percent": 1.66,
                "digital": "0:05",
                "decimal": "0.08",
                "text": "5 mins",
                "hours": 0,
                "minutes": 5
            },
            {
                "total_seconds": 0.147,
                "name": "io.flutter",
                "percent": 0.0,
                "digital": "0:00",
                "decimal": "0.00",
                "text": "0 secs",
                "hours": 0,
                "minutes": 0
            },
            {
                "total_seconds": 0.147,
                "name": "androidx.annotation",
                "percent": 0.0,
                "digital": "0:00",
                "decimal": "0.00",
                "text": "0 secs",
                "hours": 0,
                "minutes": 0
            }
        ],
        "total_seconds_including_other_language": 144298.284,
        "total_seconds": 144298.284,
        "languages": [
            {
                "name": "Dart",
                "total_seconds": 133106.343,
                "percent": 92.24,
                "digital": "36:58",
                "decimal": "36.97",
                "text": "36 hrs 58 mins",
                "hours": 36,
                "minutes": 58
            },
            {
                "name": "JSON",
                "total_seconds": 4497.953,
                "percent": 3.12,
                "digital": "1:14",
                "decimal": "1.23",
                "text": "1 hr 14 mins",
                "hours": 1,
                "minutes": 14
            },
            {
                "name": "Image (svg)",
                "total_seconds": 3635.869,
                "percent": 2.52,
                "digital": "1:00",
                "decimal": "1.00",
                "text": "1 hr",
                "hours": 1,
                "minutes": 0
            },
            {
                "name": "Python",
                "total_seconds": 2076.437,
                "percent": 1.44,
                "digital": "0:34",
                "decimal": "0.57",
                "text": "34 mins",
                "hours": 0,
                "minutes": 34
            },
            {
                "name": "YAML",
                "total_seconds": 824.33,
                "percent": 0.57,
                "digital": "0:13",
                "decimal": "0.22",
                "text": "13 mins",
                "hours": 0,
                "minutes": 13
            },
            {
                "name": "textmate",
                "total_seconds": 61.759,
                "percent": 0.04,
                "digital": "0:01",
                "decimal": "0.02",
                "text": "1 min",
                "hours": 0,
                "minutes": 1
            },
            {
                "name": "Kotlin",
                "total_seconds": 52.635,
                "percent": 0.04,
                "digital": "0:00",
                "decimal": "0.00",
                "text": "0 secs",
                "hours": 0,
                "minutes": 0
            },
            {
                "name": "ObjectiveC",
                "total_seconds": 18.65,
                "percent": 0.01,
                "digital": "0:00",
                "decimal": "0.00",
                "text": "0 secs",
                "hours": 0,
                "minutes": 0
            },
            {
                "name": "XML",
                "total_seconds": 9.871,
                "percent": 0.01,
                "digital": "0:00",
                "decimal": "0.00",
                "text": "0 secs",
                "hours": 0,
                "minutes": 0
            },
            {
                "name": "Cocoa",
                "total_seconds": 3.339,
                "percent": 0.0,
                "digital": "0:00",
                "decimal": "0.00",
                "text": "0 secs",
                "hours": 0,
                "minutes": 0
            },
            {
                "name": "CMake",
                "total_seconds": 3.223,
                "percent": 0.0,
                "digital": "0:00",
                "decimal": "0.00",
                "text": "0 secs",
                "hours": 0,
                "minutes": 0
            },
            {
                "name": "Markdown",
                "total_seconds": 3.013,
                "percent": 0.0,
                "digital": "0:00",
                "decimal": "0.00",
                "text": "0 secs",
                "hours": 0,
                "minutes": 0
            },
            {
                "name": "JavaScript",
                "total_seconds": 2.374,
                "percent": 0.0,
                "digital": "0:00",
                "decimal": "0.00",
                "text": "0 secs",
                "hours": 0,
                "minutes": 0
            },
            {
                "name": "Java Properties",
                "total_seconds": 1.117,
                "percent": 0.0,
                "digital": "0:00",
                "decimal": "0.00",
                "text": "0 secs",
                "hours": 0,
                "minutes": 0
            },
            {
                "name": "Text",
                "total_seconds": 0.961,
                "percent": 0.0,
                "digital": "0:00",
                "decimal": "0.00",
                "text": "0 secs",
                "hours": 0,
                "minutes": 0
            },
            {
                "name": "Java",
                "total_seconds": 0.147,
                "percent": 0.0,
                "digital": "0:00",
                "decimal": "0.00",
                "text": "0 secs",
                "hours": 0,
                "minutes": 0
            },
            {
                "name": "CMakeLists.txt",
                "total_seconds": 0.092,
                "percent": 0.0,
                "digital": "0:00",
                "decimal": "0.00",
                "text": "0 secs",
                "hours": 0,
                "minutes": 0
            },
            {
                "name": "Shell Script",
                "total_seconds": 0.092,
                "percent": 0.0,
                "digital": "0:00",
                "decimal": "0.00",
                "text": "0 secs",
                "hours": 0,
                "minutes": 0
            },
            {
                "name": "Swift",
                "total_seconds": 0.071,
                "percent": 0.0,
                "digital": "0:00",
                "decimal": "0.00",
                "text": "0 secs",
                "hours": 0,
                "minutes": 0
            },
            {
                "name": "C++",
                "total_seconds": 0.008,
                "percent": 0.0,
                "digital": "0:00",
                "decimal": "0.00",
                "text": "0 secs",
                "hours": 0,
                "minutes": 0
            }
        ],
        "human_readable_daily_average": "6 hrs 40 mins",
        "percent_calculated": 100,
        "human_readable_total": "40 hrs 4 mins",
        "is_cached": true,
        "username": "addi_kichi",
        "is_including_today": false,
        "human_readable_range": "last week",
        "is_coding_activity_visible": false,
        "is_language_usage_visible": false,
        "is_editor_usage_visible": false,
        "is_category_usage_visible": false,
        "is_os_usage_visible": false
    }
}