{
    "data": {
        "id": "74128f40-b5cb-4aef-83a8-f26fcd0ca0df",
        "user_id": "d44d9645-f329-4729-a92d-c1c4ce039e23",
        "range": "last_7_days",
        "start": "2026-02-14T23:00:00Z",
        "end": "2026-02-21T22:59:59Z",
        "timeout": 15,
        "writes_only": false,
        "timezone": "Europe/Paris",
        "ai_additions": 0,
        "ai_deletions": 0,
        "human_additions": 0,
        "human_deletions": 0,
        "holidays": 0,
        "status": "ok",
        "created_at": "2026-02-19T02:47:33Z",
        "modified_at": "2026-02-22T01:03:30Z",
        "human_readable_total": "35 hrs 59 mins",
        "best_day": {
            "date": "2026-02-21",
            "total_seconds": 40166.996,
            "text": "11 hrs 9 mins"
        },
        "editors": [
            {
                "total_seconds": 129599.35,
                "name": "Android Studio",
                "percent": 100.0,
                "digital": "35:59",
                "decimal": "35.98",
                "text": "35 hrs 59 mins",
                "hours": 35,
                "minutes": 59
            }
        ],
        "percent_calculated": 100,
        "languages": [
            {
                "name": "Dart",
                "total_seconds": 85553.922,
                "percent": 66.01,
                "digital": "23:45",
                "decimal": "23.75",
                "text": "23 hrs 45 mins",
                "hours": 23,
                "minutes": 45
            },
            {
                "name": "YAML",
                "total_seconds": 15924.739,
                "percent": 12.29,
                "digital": "4:25",
                "decimal": "4.42",
                "text": "4 hrs 25 mins",
                "hours": 4,
                "minutes": 25
            },
            {
                "name": "TOML",
                "total_seconds": 9242.001,
                "percent": 7.13,
                "digital": "2:34",
                "decimal": "2.57",
                "text": "2 hrs 34 mins",
                "hours": 2,
                "minutes": 34
            },
            {
                "name": "JSON",
                "total_seconds": 8357.706,
                "percent": 6.45,
                "digital": "2:19",
                "decimal": "2.32",
                "text": "2 hrs 19 mins",
                "hours": 2,
                "minutes": 19
            },
            {
                "name": "HTML",
                "total_seconds": 2530.423,
                "percent": 1.95,
                "digital": "0:42",
                "decimal": "0.70",
                "text": "42 mins",
                "hours": 0,
                "minutes": 42
            },
            {
                "name": "Bash",
                "total_seconds": 1689.903,
                "percent": 1.3,
                "digital": "0:28",
                "decimal": "0.47",
                "text": "28 mins",
                "hours": 0,
                "minutes": 28
            },
            {
                "name": "Text",
                "total_seconds": 1162.838,
                "percent": 0.9,
                "digital": "0:19",
                "decimal": "0.32",
                "text": "19 mins",
                "hours": 0,
                "minutes": 19
            },
            {
                "name": "Image (svg)",
                "total_seconds": 1068.152,
                "percent": 0.82,
                "digital": "0:17",
                "decimal": "0.28",
                "text": "17 mins",
                "hours": 0,
                "minutes": 17
            },
            {
                "name": "IDEA_MODULE",
                "total_seconds": 1018.106,
                "percent": 0.79,
                "digital": "0:16",
                "decimal": "0.27",
                "text": "16 mins",
                "hours": 0,
                "minutes": 16
            },
            {
                "name": "GitIgnore file",
                "total_seconds": 666.938,
                "percent": 0.51,
                "digital": "0:11",
                "decimal": "0.18",
                "text": "11 mins",
                "hours": 0,
                "minutes": 11
            },
            {
                "name": ".env file",
                "total_seconds": 496.504,
                "percent": 0.38,
                "digital": "0:08",
                "decimal": "0.13",
                "text": "8 mins",
                "hours": 0,
                "minutes": 8
            },
            {
                "name": "PowerShell",
                "total_seconds": 381.206,
                "percent": 0.29,
                "digital": "0:06",
                "decimal": "0.10",
                "text": "6 mins",
                "hours": 0,
                "minutes": 6
            },
            {
                "name": "Shell Script",
                "total_seconds": 374.849,
                "percent": 0.29,
                "digital": "0:06",
                "decimal": "0.10",
                "text": "6 mins",
                "hours": 0,
                "minutes": 6
            },
            {
                "name": "Markdown",
                "total_seconds": 352.114,
                "percent": 0.27,
                "digital": "0:05",
                "decimal": "0.08",
                "text": "5 mins",
                "hours": 0,
                "minutes": 5
            },
            {
                "name": "JavaScript",
                "total_seconds": 317.179,
                "percent": 0.24,
                "digital": "0:05",
                "decimal": "0.08",
                "text": "5 mins",
                "hours": 0,
                "minutes": 5
            },
            {
                "name": "XML",
                "total_seconds": 242.499,
                "percent": 0.19,
                "digital": "0:04",
                "decimal": "0.07",
                "text": "4 mins",
                "hours": 0,
                "minutes": 4
            },
            {
                "name": "Python",
                "total_seconds": 101.82,
                "percent": 0.08,
                "digital": "0:01",
                "decimal": "0.02",
                "text": "1 min",
                "hours": 0,
                "minutes": 1
            },
            {
                "name": "textmate",
                "total_seconds": 83.593,
                "percent": 0.06,
                "digital": "0:01",
                "decimal": "0.02",
                "text": "1 min",
                "hours": 0,
                "minutes": 1
            },
            {
                "name": "Swift",
                "total_seconds": 24.749,
                "percent": 0.02,
                "digital": "0:00",
                "decimal": "0.00",
                "text": "0 secs",
                "hours": 0,
                "minutes": 0
            },
            {
                "name": "Log",
                "total_seconds": 8.274,
                "percent": 0.01,
                "digital": "0:00",
                "decimal": "0.00",
                "text": "0 secs",
                "hours": 0,
                "minutes": 0
            },
            {
                "name": "Cocoa",
                "total_seconds": 0.936,
                "percent": 0.0,
                "digital": "0:00",
                "decimal": "0.00",
                "text": "0 secs",
                "hours": 0,
                "minutes": 0
            },
            {
                "name": "CMake",
                "total_seconds": 0.727,
                "percent": 0.0,
                "digital": "0:00",
                "decimal": "0.00",
                "text": "0 secs",
                "hours": 0,
                "minutes": 0
            },
            {
                "name": "ObjectiveC",
                "total_seconds": 0.149,
                "percent": 0.0,
                "digital": "0:00",
                "decimal": "0.00",
                "text": "0 secs",
                "hours": 0,
                "minutes": 0
            },
            {
                "name": "CMakeLists.txt",
                "total_seconds": 0.02,
                "percent": 0.0,
                "digital": "0:00",
                "decimal": "0.00",
                "text": "0 secs",
                "hours": 0,
                "minutes": 0
            },
            {
                "name": "C++",
                "total_seconds": 0.003,
                "percent": 0.0,
                "digital": "0:00",
                "decimal": "0.00",
                "text": "0 secs",
                "hours": 0,
                "minutes": 0
            }
        ],
        "projects": [
            {
                "total_seconds": 79800.876,
                "name": "emap_services",
                "ai_additions": 0,
                "ai_deletions": 0,
                "human_additions": 0,
                "human_deletions": 0,
                "percent": 61.58,
                "digital": "22:10",
                "decimal": "22.17",
                "text": "22 hrs 10 mins",
                "hours": 22,
                "minutes": 10
            },
            {
                "total_seconds": 39189.96,
                "name": "portefolio",
                "ai_additions": 0,
                "ai_deletions": 0,
                "human_additions": 0,
                "human_deletions": 0,
                "percent": 30.24,
                "digital": "10:53",
                "decimal": "10.88",
                "text": "10 hrs 53 mins",
                "hours": 10,
                "minutes": 53
            },
            {
                "total_seconds": 8044.062,
                "name": "shared_models",
                "ai_additions": 0,
                "ai_deletions": 0,
                "human_additions": 0,
                "human_deletions": 0,
                "percent": 6.21,
                "digital": "2:14",
                "decimal": "2.23",
                "text": "2 hrs 14 mins",
                "hours": 2,
                "minutes": 14
            },
            {
                "total_seconds": 2513.834,
                "name": "shared_models-ff2b47337711f30a867f8660b873ded2ad5aa9c6",
                "ai_additions": 0,
                "ai_deletions": 0,
                "human_additions": 0,
                "human_deletions": 0,
                "percent": 1.94,
                "digital": "0:41",
                "decimal": "0.68",
                "text": "41 mins",
                "hours": 0,
                "minutes": 41
            },
            {
                "total_seconds": 50.618,
                "name": "default",
                "ai_additions": 0,
                "ai_deletions": 0,
                "human_additions": 0,
                "human_deletions": 0,
                "percent": 0.04,
                "digital": "0:00",
                "decimal": "0.00",
                "text": "0 secs",
                "hours": 0,
                "minutes": 0
            }
        ],
        "is_already_updating": false,
        "human_readable_total_including_other_language": "35 hrs 59 mins",
        "is_up_to_date_pending_future": false,
        "dependencies": [
            {
                "total_seconds": 1855.643,
                "name": "\"flutter_bootstrap.js\"",
                "percent": 16.14,
                "digital": "0:30",
                "decimal": "0.50",
                "text": "30 mins",
                "hours": 0,
                "minutes": 30
            },
            {
                "total_seconds": 508.285,
                "name": "\"https://maps.googleapis.com/maps/api/js?key=AIzaSyAFjEUfY0mT-7CUf7Jeze3LxlKbUVQkNKs\"",
                "percent": 4.42,
                "digital": "0:08",
                "decimal": "0.13",
                "text": "8 mins",
                "hours": 0,
                "minutes": 8
            },
            {
                "total_seconds": 311.897,
                "name": "best_day",
                "percent": 2.71,
                "digital": "0:05",
                "decimal": "0.08",
                "text": "5 mins",
                "hours": 0,
                "minutes": 5
            },
            {
                "total_seconds": 311.897,
                "name": "categories",
                "percent": 2.71,
                "digital": "0:05",
                "decimal": "0.08",
                "text": "5 mins",
                "hours": 0,
                "minutes": 5
            },
            {
                "total_seconds": 311.897,
                "name": "is_up_to_date_pending_future",
                "percent": 2.71,
                "digital": "0:05",
                "decimal": "0.08",
                "text": "5 mins",
                "hours": 0,
                "minutes": 5
            },
            {
                "total_seconds": 311.897,
                "name": "is_stuck",
                "percent": 2.71,
                "digital": "0:05",
                "decimal": "0.08",
                "text": "5 mins",
                "hours": 0,
                "minutes": 5
            },
            {
                "total_seconds": 311.897,
                "name": "total_seconds",
                "percent": 2.71,
                "digital": "0:05",
                "decimal": "0.08",
                "text": "5 mins",
                "hours": 0,
                "minutes": 5
            },
            {
                "total_seconds": 311.897,
                "name": "is_up_to_date",
                "percent": 2.71,
                "digital": "0:05",
                "decimal": "0.08",
                "text": "5 mins",
                "hours": 0,
                "minutes": 5
            },
            {
                "total_seconds": 311.897,
                "name": "daily_average_including_other_language",
                "percent": 2.71,
                "digital": "0:05",
                "decimal": "0.08",
                "text": "5 mins",
                "hours": 0,
                "minutes": 5
            },
            {
                "total_seconds": 311.897,
                "name": "projects",
                "percent": 2.71,
                "digital": "0:05",
                "decimal": "0.08",
                "text": "5 mins",
                "hours": 0,
                "minutes": 5
            },
            {
                "total_seconds": 311.897,
                "name": "editors",
                "percent": 2.71,
                "digital": "0:05",
                "decimal": "0.08",
                "text": "5 mins",
                "hours": 0,
                "minutes": 5
            },
            {
                "total_seconds": 311.897,
                "name": "is_language_usage_visible",
                "percent": 2.71,
                "digital": "0:05",
                "decimal": "0.08",
                "text": "5 mins",
                "hours": 0,
                "minutes": 5
            },
            {
                "total_seconds": 311.897,
                "name": "is_editor_usage_visible",
                "percent": 2.71,
                "digital": "0:05",
                "decimal": "0.08",
                "text": "5 mins",
                "hours": 0,
                "minutes": 5
            },
            {
                "total_seconds": 311.897,
                "name": "percent_calculated",
                "percent": 2.71,
                "digital": "0:05",
                "decimal": "0.08",
                "text": "5 mins",
                "hours": 0,
                "minutes": 5
            },
            {
                "total_seconds": 311.897,
                "name": "daily_average",
                "percent": 2.71,
                "digital": "0:05",
                "decimal": "0.08",
                "text": "5 mins",
                "hours": 0,
                "minutes": 5
            },
            {
                "total_seconds": 311.897,
                "name": "is_including_today",
                "percent": 2.71,
                "digital": "0:05",
                "decimal": "0.08",
                "text": "5 mins",
                "hours": 0,
                "minutes": 5
            },
            {
                "total_seconds": 311.897,
                "name": "human_readable_daily_average",
                "percent": 2.71,
                "digital": "0:05",
                "decimal": "0.08",
                "text": "5 mins",
                "hours": 0,
                "minutes": 5
            },
            {
                "total_seconds": 311.897,
                "name": "total_seconds_including_other_language",
                "percent": 2.71,
                "digital": "0:05",
                "decimal": "0.08",
                "text": "5 mins",
                "hours": 0,
                "minutes": 5
            },
            {
                "total_seconds": 311.897,
                "name": "is_os_usage_visible",
                "percent": 2.71,
                "digital": "0:05",
                "decimal": "0.08",
                "text": "5 mins",
                "hours": 0,
                "minutes": 5
            },
            {
                "total_seconds": 311.897,
                "name": "machines",
                "percent": 2.71,
                "digital": "0:05",
                "decimal": "0.08",
                "text": "5 mins",
                "hours": 0,
                "minutes": 5
            },
            {
                "total_seconds": 311.897,
                "name": "operating_systems",
                "percent": 2.71,
                "digital": "0:05",
                "decimal": "0.08",
                "text": "5 mins",
                "hours": 0,
                "minutes": 5
            },
            {
                "total_seconds": 311.897,
                "name": "days_minus_holidays",
                "percent": 2.71,
                "digital": "0:05",
                "decimal": "0.08",
                "text": "5 mins",
                "hours": 0,
                "minutes": 5
            },
            {
                "total_seconds": 311.897,
                "name": "is_already_updating",
                "percent": 2.71,
                "digital": "0:05",
                "decimal": "0.08",
                "text": "5 mins",
                "hours": 0,
                "minutes": 5
            },
            {
                "total_seconds": 311.897,
                "name": "is_cached",
                "percent": 2.71,
                "digital": "0:05",
                "decimal": "0.08",
                "text": "5 mins",
                "hours": 0,
                "minutes": 5
            },
            {
                "total_seconds": 311.897,
                "name": "human_readable_range",
                "percent": 2.71,
                "digital": "0:05",
                "decimal": "0.08",
                "text": "5 mins",
                "hours": 0,
                "minutes": 5
            },
            {
                "total_seconds": 311.897,
                "name": "is_coding_activity_visible",
                "percent": 2.71,
                "digital": "0:05",
                "decimal": "0.08",
                "text": "5 mins",
                "hours": 0,
                "minutes": 5
            },
            {
                "total_seconds": 311.897,
                "name": "is_category_usage_visible",
                "percent": 2.71,
                "digital": "0:05",
                "decimal": "0.08",
                "text": "5 mins",
                "hours": 0,
                "minutes": 5
            },
            {
                "total_seconds": 311.897,
                "name": "username",
                "percent": 2.71,
                "digital": "0:05",
                "decimal": "0.08",
                "text": "5 mins",
                "hours": 0,
                "minutes": 5
            },
            {
                "total_seconds": 205.419,
                "name": "\"https://cdn.emailjs.com/sdk/3.2/email.min.js\"",
                "percent": 1.79,
                "digital": "0:03",
                "decimal": "0.05",
                "text": "3 mins",
                "hours": 0,
                "minutes": 3
            },
            {
                "total_seconds": 205.06,
                "name": "node-fetch",
                "percent": 1.78,
                "digital": "0:03",
                "decimal": "0.05",
                "text": "3 mins",
                "hours": 0,
                "minutes": 3
            },
            {
                "total_seconds": 101.82,
                "name": "pathlib",
                "percent": 0.89,
                "digital": "0:01",
                "decimal": "0.02",
                "text": "1 min",
                "hours": 0,
                "minutes": 1
            },
            {
                "total_seconds": 101.82,
                "name": "argparse",
                "percent": 0.89,
                "digital": "0:01",
                "decimal": "0.02",
                "text": "1 min",
                "hours": 0,
                "minutes": 1
            },
            {
                "total_seconds": 101.82,
                "name": "tqdm",
                "percent": 0.89,
                "digital": "0:01",
                "decimal": "0.02",
                "text": "1 min",
                "hours": 0,
                "minutes": 1
            },
            {
                "total_seconds": 101.82,
                "name": "shutil",
                "percent": 0.89,
                "digital": "0:01",
                "decimal": "0.02",
                "text": "1 min",
                "hours": 0,
                "minutes": 1
            },
            {
                "total_seconds": 101.82,
                "name": "typing",
                "percent": 0.89,
                "digital": "0:01",
                "decimal": "0.02",
                "text": "1 min",
                "hours": 0,
                "minutes": 1
            },
            {
                "total_seconds": 101.82,
                "name": "PIL",
                "percent": 0.89,
                "digital": "0:01",
                "decimal": "0.02",
                "text": "1 min",
                "hours": 0,
                "minutes": 1
            }
        ],
        "daily_average": 18514.0,
        "is_up_to_date": true,
        "operating_systems": [
            {
                "total_seconds": 129599.35,
                "name": "Windows",
                "percent": 100.0,
                "digital": "35:59",
                "decimal": "35.98",
                "text": "35 hrs 59 mins",
                "hours": 35,
                "minutes": 59
            }
        ],
        "categories": [
            {
                "name": "Coding",
                "total_seconds": 127397.675,
                "percent": 98.3,
                "digital": "35:23",
                "decimal": "35.38",
                "text": "35 hrs 23 mins",
                "hours": 35,
                "minutes": 23
            },
            {
                "name": "Writing Tests",
                "total_seconds": 1849.561,
                "percent": 1.43,
                "digital": "0:30",
                "decimal": "0.50",
                "text": "30 mins",
                "hours": 0,
                "minutes": 30
            },
            {
                "name": "Writing Docs",
                "total_seconds": 352.114,
                "percent": 0.27,
                "digital": "0:05",
                "decimal": "0.08",
                "text": "5 mins",
                "hours": 0,
                "minutes": 5
            }
        ],
        "days_including_holidays": 7,
        "days_minus_holidays": 7,
        "total_seconds": 129599.35,
        "human_readable_daily_average": "5 hrs 8 mins",
        "is_stuck": false,
        "daily_average_including_other_language": 18514.0,
        "total_seconds_including_other_language": 129599.35,
        "human_readable_daily_average_including_other_language": "5 hrs 8 mins",
        "machines": [
            {
                "total_seconds": 129599.35,
                "name": "LAPTOP-CUKQT8S6",
                "machine_name_id": "ccfe4022-9651-4a7c-a1e6-d1fba97eed73",
                "percent": 100.0,
                "digital": "35:59",
                "decimal": "35.98",
                "text": "35 hrs 59 mins",
                "hours": 35,
                "minutes": 59
            }
        ],
        "is_cached": true,
        "username": "addi_kichi",
        "is_including_today": false,
        "human_readable_range": "last week",
        "is_coding_activity_visible": false,
        "is_language_usage_visible": false,
        "is_editor_usage_visible": false,
        "is_category_usage_visible": false,
        "is_os_usage_visible": false
    }
}